catcli/__init__.py
catcli/catalog.py
catcli/catcli.py
catcli/colors.py
catcli/decomp.py
catcli/exceptions.py
catcli/fuser.py
catcli/logger.py
catcli/noder.py
catcli/nodes.py
catcli/nodes_utils.py
catcli/printer_csv.py
catcli/printer_native.py
catcli/utils.py
catcli/version.py
catcli/walker.py
catcli-1.0.dist-info/LICENSE
catcli-1.0.dist-info/METADATA
catcli-1.0.dist-info/WHEEL
catcli-1.0.dist-info/entry_points.txt
catcli-1.0.dist-info/top_level.txt
catcli-1.0.dist-info/RECORD
