Metadata-Version: 2.1
Name: catcli
Version: 1.0
Summary: The command line catalog tool for your offline data
Home-page: https://github.com/deadc0de6/catcli
Author: deadc0de6
Author-email: deadc0de6@foo.bar
License: GPLv3
Download-URL: https://github.com/deadc0de6/catcli/archive/v1.0.tar.gz
Keywords: catalog commandline indexer offline
Platform: UNKNOWN
Classifier: Development Status :: 5 - Production/Stable
Classifier: Programming Language :: Python :: 3.7
Classifier: Programming Language :: Python :: 3.8
Classifier: Programming Language :: Python :: 3.9
Classifier: Programming Language :: Python :: 3.10
Classifier: Programming Language :: Python :: 3.11
Classifier: License :: OSI Approved :: GNU General Public License v3 (GPLv3)
Requires-Python: >=3
Requires-Dist: docopt
Requires-Dist: types-docopt
Requires-Dist: anytree
Requires-Dist: pyfzf
Requires-Dist: fusepy
Requires-Dist: natsort
Requires-Dist: cmd2
Requires-Dist: gnureadline
Provides-Extra: dev
Requires-Dist: check-manifest ; extra == 'dev'
Provides-Extra: test
Requires-Dist: coverage ; extra == 'test'
Requires-Dist: pytest ; extra == 'test'
Requires-Dist: pytest-cov ; extra == 'test'
